cxstat/__init__.py
cxstat/claude.py
cxstat/claude_models.py
cxstat/log_models.py
cxstat/logger.py
cxstat/models.py
cxstat/service.py
cxstat/theme.py
cxstat/utils.py
cxstat/view.py
cxstat/cli/__init__.py
cxstat/cli/main.py
cxstat/cli/options.py
cxstat-0.1.2.dist-info/METADATA
cxstat-0.1.2.dist-info/WHEEL
cxstat-0.1.2.dist-info/entry_points.txt
cxstat-0.1.2.dist-info/licenses/LICENSE
cxstat-0.1.2.dist-info/RECORD
