Metadata-Version: 2.4
Name: cxstat
Version: 0.1.2
Summary: Token usage analytics for Codex CLI sessions
Project-URL: Repository, https://github.com/takeshiD/cxstat
Author-email: takeshid <goriponikeike55@gmail.com>
License-Expression: MIT
License-File: LICENSE
Keywords: codex,llm,mcp,tokenusage
Classifier: Development Status :: 4 - Beta
Classifier: Environment :: Console
Classifier: Intended Audience :: Developers
Classifier: License :: OSI Approved :: MIT License
Classifier: Programming Language :: Python
Classifier: Programming Language :: Python :: 3.12
Requires-Python: >=3.12
Requires-Dist: pydantic>=2.7
Requires-Dist: pytest>=8.3
Requires-Dist: rich>=13
Requires-Dist: tiktoken>=0.12.0
Requires-Dist: typer>=0.12
